{
    "xmlName": {
        "Space": "http://www.omg.org/spec/DMN/20151101/dmn11.xsd",
        "Local": "definitions"
    },
    "xmlns": "http://www.omg.org/spec/DMN/20151101/dmn11.xsd",
    "id": "definitions",
    "name": "definitions",
    "namespace": "http://camunda.org/schema/1.0/dmn",
    "decision": {
        "xmlName": {
            "Space": "http://www.omg.org/spec/DMN/20151101/dmn11.xsd",
            "Local": "decision"
        },
        "id": "fss-user-provisioning-roles-rules",
        "name": "fss-user-provisioning-roles-rules",
        "decisionTable": {
            "xmlName": {
                "Space": "http://www.omg.org/spec/DMN/20151101/dmn11.xsd",
                "Local": "decisionTable"
            },
            "id": "decisionTable",
            "hitPolicy": "COLLECT",
            "input": [
                {
                    "xmlName": {
                        "Space": "http://www.omg.org/spec/DMN/20151101/dmn11.xsd",
                        "Local": "input"
                    },
                    "id": "input1",
                    "label": "jobcode",
                    "inputExpression": [
                        {
                            "xmlName": {
                                "Space": "http://www.omg.org/spec/DMN/20151101/dmn11.xsd",
                                "Local": "inputExpression"
                            },
                            "id": "inputExpression1",
                            "typeRef": "string",
                            "text": "jobCode"
                        }
                    ]
                }
            ],
            "output": [
                {
                    "xmlName": {
                        "Space": "http://www.omg.org/spec/DMN/20151101/dmn11.xsd",
                        "Local": "output"
                    },
                    "id": "output1",
                    "label": "Job Code Name",
                    "name": "jobCodeDescription",
                    "typeRef": "string"
                },
                {
                    "xmlName": {
                        "Space": "http://www.omg.org/spec/DMN/20151101/dmn11.xsd",
                        "Local": "output"
                    },
                    "id": "OutputClause_02hqea0",
                    "label": "Flow Type",
                    "name": "flow",
                    "typeRef": "string"
                }
            ],
            "rule": [
                {
                    "xmlName": {
                        "Space": "http://www.omg.org/spec/DMN/20151101/dmn11.xsd",
                        "Local": "rule"
                    },
                    "id": "row-796075197-1",
                    "inputEntry": [
                        {
                            "xmlName": {
                                "Space": "http://www.omg.org/spec/DMN/20151101/dmn11.xsd",
                                "Local": "inputEntry"
                            },
                            "id": "UnaryTests_1uoxv0j",
                            "text": "\"4306\""
                        }
                    ],
                    "outputEntry": [
                        {
                            "xmlName": {
                                "Space": "http://www.omg.org/spec/DMN/20151101/dmn11.xsd",
                                "Local": "outputEntry"
                            },
                            "id": "LiteralExpression_179nc2q",
                            "description": "",
                            "text": "\"GX instructor\""
                        },
                        {
                            "xmlName": {
                                "Space": "http://www.omg.org/spec/DMN/20151101/dmn11.xsd",
                                "Local": "outputEntry"
                            },
                            "id": "LiteralExpression_14cuxah",
                            "description": "",
                            "text": "\"GXI\""
                        }
                    ]
                },
                {
                    "xmlName": {
                        "Space": "http://www.omg.org/spec/DMN/20151101/dmn11.xsd",
                        "Local": "rule"
                    },
                    "id": "row-796075197-2",
                    "inputEntry": [
                        {
                            "xmlName": {
                                "Space": "http://www.omg.org/spec/DMN/20151101/dmn11.xsd",
                                "Local": "inputEntry"
                            },
                            "id": "UnaryTests_1p4qtzz",
                            "text": "\"5551\""
                        }
                    ],
                    "outputEntry": [
                        {
                            "xmlName": {
                                "Space": "http://www.omg.org/spec/DMN/20151101/dmn11.xsd",
                                "Local": "outputEntry"
                            },
                            "id": "LiteralExpression_1rodvih",
                            "description": "",
                            "text": "\"Sr. Director, GX Operations\""
                        },
                        {
                            "xmlName": {
                                "Space": "http://www.omg.org/spec/DMN/20151101/dmn11.xsd",
                                "Local": "outputEntry"
                            },
                            "id": "LiteralExpression_0xe0o5p",
                            "description": "",
                            "text": "\"GXI\""
                        }
                    ]
                },
                {
                    "xmlName": {
                        "Space": "http://www.omg.org/spec/DMN/20151101/dmn11.xsd",
                        "Local": "rule"
                    },
                    "id": "row-796075197-3",
                    "inputEntry": [
                        {
                            "xmlName": {
                                "Space": "http://www.omg.org/spec/DMN/20151101/dmn11.xsd",
                                "Local": "inputEntry"
                            },
                            "id": "UnaryTests_1owa5gp",
                            "text": "\"7046\""
                        }
                    ],
                    "outputEntry": [
                        {
                            "xmlName": {
                                "Space": "http://www.omg.org/spec/DMN/20151101/dmn11.xsd",
                                "Local": "outputEntry"
                            },
                            "id": "LiteralExpression_14db8v5",
                            "description": "",
                            "text": "\"Regional GX Director\""
                        },
                        {
                            "xmlName": {
                                "Space": "http://www.omg.org/spec/DMN/20151101/dmn11.xsd",
                                "Local": "outputEntry"
                            },
                            "id": "LiteralExpression_0sii979",
                            "description": "",
                            "text": "\"GXI\""
                        }
                    ]
                },
                {
                    "xmlName": {
                        "Space": "http://www.omg.org/spec/DMN/20151101/dmn11.xsd",
                        "Local": "rule"
                    },
                    "id": "row-796075197-4",
                    "inputEntry": [
                        {
                            "xmlName": {
                                "Space": "http://www.omg.org/spec/DMN/20151101/dmn11.xsd",
                                "Local": "inputEntry"
                            },
                            "id": "UnaryTests_06s5qf9",
                            "text": "\"8851\""
                        }
                    ],
                    "outputEntry": [
                        {
                            "xmlName": {
                                "Space": "http://www.omg.org/spec/DMN/20151101/dmn11.xsd",
                                "Local": "outputEntry"
                            },
                            "id": "LiteralExpression_0e1wyk4",
                            "description": "",
                            "text": "\"Group Fitness Ops Manager\""
                        },
                        {
                            "xmlName": {
                                "Space": "http://www.omg.org/spec/DMN/20151101/dmn11.xsd",
                                "Local": "outputEntry"
                            },
                            "id": "LiteralExpression_0coohzu",
                            "description": "",
                            "text": "\"GXI\""
                        }
                    ]
                },
                {
                    "xmlName": {
                        "Space": "http://www.omg.org/spec/DMN/20151101/dmn11.xsd",
                        "Local": "rule"
                    },
                    "id": "row-796075197-5",
                    "inputEntry": [
                        {
                            "xmlName": {
                                "Space": "http://www.omg.org/spec/DMN/20151101/dmn11.xsd",
                                "Local": "inputEntry"
                            },
                            "id": "UnaryTests_1rsa2s8",
                            "text": "\"5443\""
                        }
                    ],
                    "outputEntry": [
                        {
                            "xmlName": {
                                "Space": "http://www.omg.org/spec/DMN/20151101/dmn11.xsd",
                                "Local": "outputEntry"
                            },
                            "id": "LiteralExpression_1wtaeg8",
                            "description": "",
                            "text": "\"VP, GX Ops\""
                        },
                        {
                            "xmlName": {
                                "Space": "http://www.omg.org/spec/DMN/20151101/dmn11.xsd",
                                "Local": "outputEntry"
                            },
                            "id": "LiteralExpression_1ghejpp",
                            "description": "",
                            "text": "\"GXI\""
                        }
                    ]
                },
                {
                    "xmlName": {
                        "Space": "http://www.omg.org/spec/DMN/20151101/dmn11.xsd",
                        "Local": "rule"
                    },
                    "id": "row-796075197-6",
                    "inputEntry": [
                        {
                            "xmlName": {
                                "Space": "http://www.omg.org/spec/DMN/20151101/dmn11.xsd",
                                "Local": "inputEntry"
                            },
                            "id": "UnaryTests_11nykfh",
                            "text": "\"5389\""
                        }
                    ],
                    "outputEntry": [
                        {
                            "xmlName": {
                                "Space": "http://www.omg.org/spec/DMN/20151101/dmn11.xsd",
                                "Local": "outputEntry"
                            },
                            "id": "LiteralExpression_1yeboy4",
                            "description": "",
                            "text": "\"Area Group X Manager\""
                        },
                        {
                            "xmlName": {
                                "Space": "http://www.omg.org/spec/DMN/20151101/dmn11.xsd",
                                "Local": "outputEntry"
                            },
                            "id": "LiteralExpression_1s0hnyv",
                            "description": "",
                            "text": "\"GXI\""
                        }
                    ]
                }
            ]
        }
    }
}